<?xml version="1.0" encoding="US-ASCII" standalone="yes"?>
<maudeml>
 <result total-rewrites="0" real-time-ms="0" cpu-time-ms="0" rewrites-per-second="0">
  <term op="setCounter" sort="#Int">
   <term op="0" sort="#Zero"/>
  </term>
 </result>
 <result total-rewrites="5751" real-time-ms="6" cpu-time-ms="6" rewrites-per-second="930131">
  <term op="&lt;_>_&lt;/_>" sort="BagItem">
   <term op="generatedTop" sort="CellLabel"/>
   <term op="&lt;_>_&lt;/_>" sort="BagItem">
    <term op="T" sort="CellLabel"/>
    <term op="__" sort="NeBag">
     <term op="&lt;_>_&lt;/_>" sort="BagItem">
      <term op="k" sort="CellLabel"/>
      <term op="_`(_`)" sort="KItem">
       <term op="'INSERTINTO_`(_`)VALUES`(_`);" sort="KLabel"/>
       <term op="_`,`,_" sort="NeKList">
        <term op="_`(_`)" sort="KItem">
         <term op="#token" sort="KLabel">
          <term op="&quot;Id&quot;" sort="#String"/>
          <term op="&quot;Prova&quot;" sort="#String"/>
         </term>
         <term op=".KList" sort="KList"/>
        </term>
        <term op="_`(_`)" sort="KItem">
         <term op="'_`,_" sort="KLabel"/>
         <term op="_`,`,_" sort="NeKList">
          <term op="_`(_`)" sort="KItem">
           <term op="#token" sort="KLabel">
            <term op="&quot;Id&quot;" sort="#String"/>
            <term op="&quot;Try&quot;" sort="#String"/>
           </term>
           <term op=".KList" sort="KList"/>
          </term>
          <term op="_`(_`)" sort="KItem">
           <term op="'_`,_" sort="KLabel"/>
           <term op="_`,`,_" sort="NeKList">
            <term op="_`(_`)" sort="KItem">
             <term op="#token" sort="KLabel">
              <term op="&quot;Id&quot;" sort="#String"/>
              <term op="&quot;Pry&quot;" sort="#String"/>
             </term>
             <term op=".KList" sort="KList"/>
            </term>
            <term op="_`(_`)" sort="KItem">
             <term op="'.List`{&quot;'_`,_&quot;`}" sort="KLabel"/>
             <term op=".KList" sort="KList"/>
            </term>
           </term>
          </term>
         </term>
        </term>
        <term op="_`(_`)" sort="KItem">
         <term op="'_`,_" sort="KLabel"/>
         <term op="_`,`,_" sort="NeKList">
          <term op="_`(_`)" sort="KItem">
           <term op="#_" sort="KLabel">
            <term op="sNat_" number="7" sort="#NzNat">
             <term op="0" sort="#Zero"/>
            </term>
           </term>
           <term op=".KList" sort="KList"/>
          </term>
          <term op="_`(_`)" sort="KItem">
           <term op="'.List`{&quot;'_`,_&quot;`}" sort="KLabel"/>
           <term op=".KList" sort="KList"/>
          </term>
         </term>
        </term>
       </term>
      </term>
      <term op="k" sort="CellLabel"/>
     </term>
     <term op="&lt;_>_&lt;/_>" sort="BagItem">
      <term op="database" sort="CellLabel"/>
      <term op="__" sort="NeBag">
       <term op="&lt;_>_&lt;/_>" sort="BagItem">
        <term op="database-name" sort="CellLabel"/>
        <term op="_`(_`)" sort="KItem">
         <term op="Set2KLabel_" sort="KLabel">
          <term op="SetItem" sort="SetItem">
           <term op="_`(_`)" sort="KItem">
            <term op="#token" sort="KLabel">
             <term op="&quot;Id&quot;" sort="#String"/>
             <term op="&quot;Spy&quot;" sort="#String"/>
            </term>
            <term op=".KList" sort="KList"/>
           </term>
          </term>
         </term>
         <term op=".KList" sort="KList"/>
        </term>
        <term op="database-name" sort="CellLabel"/>
       </term>
       <term op="&lt;_>_&lt;/_>" sort="BagItem">
        <term op="tables" sort="CellLabel"/>
        <term op="__" sort="NeBag">
         <term op="&lt;_>_&lt;/_>" sort="BagItem">
          <term op="table" sort="CellLabel"/>
          <term op="__" sort="NeBag">
           <term op="&lt;_>_&lt;/_>" sort="BagItem">
            <term op="schema" sort="CellLabel"/>
            <term op="_`(_`)" sort="KItem">
             <term op="Map2KLabel_" sort="KLabel">
              <term op=".Map" sort="Map"/>
             </term>
             <term op=".KList" sort="KList"/>
            </term>
            <term op="schema" sort="CellLabel"/>
           </term>
           <term op="&lt;_>_&lt;/_>" sort="BagItem">
            <term op="table-name" sort="CellLabel"/>
            <term op="_`(_`)" sort="KItem">
             <term op="Set2KLabel_" sort="KLabel">
              <term op="SetItem" sort="SetItem">
               <term op="_`(_`)" sort="KItem">
                <term op="#token" sort="KLabel">
                 <term op="&quot;Id&quot;" sort="#String"/>
                 <term op="&quot;Newtable1&quot;" sort="#String"/>
                </term>
                <term op=".KList" sort="KList"/>
               </term>
              </term>
             </term>
             <term op=".KList" sort="KList"/>
            </term>
            <term op="table-name" sort="CellLabel"/>
           </term>
           <term op="&lt;_>_&lt;/_>" sort="BagItem">
            <term op="values" sort="CellLabel"/>
            <term op=".Bag" sort="Bag"/>
            <term op="values" sort="CellLabel"/>
           </term>
          </term>
          <term op="table" sort="CellLabel"/>
         </term>
         <term op="&lt;_>_&lt;/_>" sort="BagItem">
          <term op="table" sort="CellLabel"/>
          <term op="__" sort="NeBag">
           <term op="&lt;_>_&lt;/_>" sort="BagItem">
            <term op="schema" sort="CellLabel"/>
            <term op="_`(_`)" sort="KItem">
             <term op="Map2KLabel_" sort="KLabel">
              <term op="_|->_" sort="MapItem">
               <term op="_`(_`)" sort="KItem">
                <term op="#token" sort="KLabel">
                 <term op="&quot;Id&quot;" sort="#String"/>
                 <term op="&quot;NewAnnoAccademico&quot;" sort="#String"/>
                </term>
                <term op=".KList" sort="KList"/>
               </term>
               <term op="_`(_`)" sort="KItem">
                <term op="'SMALLINT" sort="KLabel"/>
                <term op=".KList" sort="KList"/>
               </term>
              </term>
             </term>
             <term op=".KList" sort="KList"/>
            </term>
            <term op="schema" sort="CellLabel"/>
           </term>
           <term op="&lt;_>_&lt;/_>" sort="BagItem">
            <term op="table-name" sort="CellLabel"/>
            <term op="_`(_`)" sort="KItem">
             <term op="Set2KLabel_" sort="KLabel">
              <term op="SetItem" sort="SetItem">
               <term op="_`(_`)" sort="KItem">
                <term op="#token" sort="KLabel">
                 <term op="&quot;Id&quot;" sort="#String"/>
                 <term op="&quot;NewStudent&quot;" sort="#String"/>
                </term>
                <term op=".KList" sort="KList"/>
               </term>
              </term>
             </term>
             <term op=".KList" sort="KList"/>
            </term>
            <term op="table-name" sort="CellLabel"/>
           </term>
           <term op="&lt;_>_&lt;/_>" sort="BagItem">
            <term op="values" sort="CellLabel"/>
            <term op=".Bag" sort="Bag"/>
            <term op="values" sort="CellLabel"/>
           </term>
          </term>
          <term op="table" sort="CellLabel"/>
         </term>
         <term op="&lt;_>_&lt;/_>" sort="BagItem">
          <term op="table" sort="CellLabel"/>
          <term op="__" sort="NeBag">
           <term op="&lt;_>_&lt;/_>" sort="BagItem">
            <term op="schema" sort="CellLabel"/>
            <term op="_`(_`)" sort="KItem">
             <term op="Map2KLabel_" sort="KLabel">
              <term op="__" sort="NeMap">
               <term op="_|->_" sort="MapItem">
                <term op="_`(_`)" sort="KItem">
                 <term op="#token" sort="KLabel">
                  <term op="&quot;Id&quot;" sort="#String"/>
                  <term op="&quot;Cry&quot;" sort="#String"/>
                 </term>
                 <term op=".KList" sort="KList"/>
                </term>
                <term op="_`(_`)" sort="KItem">
                 <term op="'VARCHAR" sort="KLabel"/>
                 <term op=".KList" sort="KList"/>
                </term>
               </term>
               <term op="_|->_" sort="MapItem">
                <term op="_`(_`)" sort="KItem">
                 <term op="#token" sort="KLabel">
                  <term op="&quot;Id&quot;" sort="#String"/>
                  <term op="&quot;Pry&quot;" sort="#String"/>
                 </term>
                 <term op=".KList" sort="KList"/>
                </term>
                <term op="_`(_`)" sort="KItem">
                 <term op="'VARCHAR" sort="KLabel"/>
                 <term op=".KList" sort="KList"/>
                </term>
               </term>
               <term op="_|->_" sort="MapItem">
                <term op="_`(_`)" sort="KItem">
                 <term op="#token" sort="KLabel">
                  <term op="&quot;Id&quot;" sort="#String"/>
                  <term op="&quot;Try&quot;" sort="#String"/>
                 </term>
                 <term op=".KList" sort="KList"/>
                </term>
                <term op="_`(_`)" sort="KItem">
                 <term op="'SMALLINT" sort="KLabel"/>
                 <term op=".KList" sort="KList"/>
                </term>
               </term>
              </term>
             </term>
             <term op=".KList" sort="KList"/>
            </term>
            <term op="schema" sort="CellLabel"/>
           </term>
           <term op="&lt;_>_&lt;/_>" sort="BagItem">
            <term op="table-name" sort="CellLabel"/>
            <term op="_`(_`)" sort="KItem">
             <term op="Set2KLabel_" sort="KLabel">
              <term op="SetItem" sort="SetItem">
               <term op="_`(_`)" sort="KItem">
                <term op="#token" sort="KLabel">
                 <term op="&quot;Id&quot;" sort="#String"/>
                 <term op="&quot;Prova&quot;" sort="#String"/>
                </term>
                <term op=".KList" sort="KList"/>
               </term>
              </term>
             </term>
             <term op=".KList" sort="KList"/>
            </term>
            <term op="table-name" sort="CellLabel"/>
           </term>
           <term op="&lt;_>_&lt;/_>" sort="BagItem">
            <term op="values" sort="CellLabel"/>
            <term op="__" sort="NeBag">
             <term op="&lt;_>_&lt;/_>" sort="BagItem">
              <term op="value" sort="CellLabel"/>
              <term op="_`(_`)" sort="KItem">
               <term op="Map2KLabel_" sort="KLabel">
                <term op="__" sort="NeMap">
                 <term op="_|->_" sort="MapItem">
                  <term op="_`(_`)" sort="KItem">
                   <term op="#token" sort="KLabel">
                    <term op="&quot;Id&quot;" sort="#String"/>
                    <term op="&quot;Cry&quot;" sort="#String"/>
                   </term>
                   <term op=".KList" sort="KList"/>
                  </term>
                  <term op="_`(_`)" sort="KItem">
                   <term op="'null" sort="KLabel"/>
                   <term op=".KList" sort="KList"/>
                  </term>
                 </term>
                 <term op="_|->_" sort="MapItem">
                  <term op="_`(_`)" sort="KItem">
                   <term op="#token" sort="KLabel">
                    <term op="&quot;Id&quot;" sort="#String"/>
                    <term op="&quot;Pry&quot;" sort="#String"/>
                   </term>
                   <term op=".KList" sort="KList"/>
                  </term>
                  <term op="_`(_`)" sort="KItem">
                   <term op="''_'" sort="KLabel"/>
                   <term op="_`(_`)" sort="KItem">
                    <term op="#_" sort="KLabel">
                     <term op="&quot;ciao&quot;" sort="#String"/>
                    </term>
                    <term op=".KList" sort="KList"/>
                   </term>
                  </term>
                 </term>
                 <term op="_|->_" sort="MapItem">
                  <term op="_`(_`)" sort="KItem">
                   <term op="#token" sort="KLabel">
                    <term op="&quot;Id&quot;" sort="#String"/>
                    <term op="&quot;Try&quot;" sort="#String"/>
                   </term>
                   <term op=".KList" sort="KList"/>
                  </term>
                  <term op="_`(_`)" sort="KItem">
                   <term op="#_" sort="KLabel">
                    <term op="sNat_" number="7" sort="#NzNat">
                     <term op="0" sort="#Zero"/>
                    </term>
                   </term>
                   <term op=".KList" sort="KList"/>
                  </term>
                 </term>
                </term>
               </term>
               <term op=".KList" sort="KList"/>
              </term>
              <term op="value" sort="CellLabel"/>
             </term>
             <term op="&lt;_>_&lt;/_>" sort="BagItem">
              <term op="value" sort="CellLabel"/>
              <term op="_`(_`)" sort="KItem">
               <term op="Map2KLabel_" sort="KLabel">
                <term op="__" sort="NeMap">
                 <term op="_|->_" sort="MapItem">
                  <term op="_`(_`)" sort="KItem">
                   <term op="#token" sort="KLabel">
                    <term op="&quot;Id&quot;" sort="#String"/>
                    <term op="&quot;Cry&quot;" sort="#String"/>
                   </term>
                   <term op=".KList" sort="KList"/>
                  </term>
                  <term op="_`(_`)" sort="KItem">
                   <term op="'null" sort="KLabel"/>
                   <term op=".KList" sort="KList"/>
                  </term>
                 </term>
                 <term op="_|->_" sort="MapItem">
                  <term op="_`(_`)" sort="KItem">
                   <term op="#token" sort="KLabel">
                    <term op="&quot;Id&quot;" sort="#String"/>
                    <term op="&quot;Pry&quot;" sort="#String"/>
                   </term>
                   <term op=".KList" sort="KList"/>
                  </term>
                  <term op="_`(_`)" sort="KItem">
                   <term op="'null" sort="KLabel"/>
                   <term op=".KList" sort="KList"/>
                  </term>
                 </term>
                 <term op="_|->_" sort="MapItem">
                  <term op="_`(_`)" sort="KItem">
                   <term op="#token" sort="KLabel">
                    <term op="&quot;Id&quot;" sort="#String"/>
                    <term op="&quot;Try&quot;" sort="#String"/>
                   </term>
                   <term op=".KList" sort="KList"/>
                  </term>
                  <term op="_`(_`)" sort="KItem">
                   <term op="#_" sort="KLabel">
                    <term op="sNat_" number="5" sort="#NzNat">
                     <term op="0" sort="#Zero"/>
                    </term>
                   </term>
                   <term op=".KList" sort="KList"/>
                  </term>
                 </term>
                </term>
               </term>
               <term op=".KList" sort="KList"/>
              </term>
              <term op="value" sort="CellLabel"/>
             </term>
            </term>
            <term op="values" sort="CellLabel"/>
           </term>
          </term>
          <term op="table" sort="CellLabel"/>
         </term>
         <term op="&lt;_>_&lt;/_>" sort="BagItem">
          <term op="table" sort="CellLabel"/>
          <term op="__" sort="NeBag">
           <term op="&lt;_>_&lt;/_>" sort="BagItem">
            <term op="schema" sort="CellLabel"/>
            <term op="_`(_`)" sort="KItem">
             <term op="Map2KLabel_" sort="KLabel">
              <term op="__" sort="NeMap">
               <term op="_|->_" sort="MapItem">
                <term op="_`(_`)" sort="KItem">
                 <term op="#token" sort="KLabel">
                  <term op="&quot;Id&quot;" sort="#String"/>
                  <term op="&quot;A&quot;" sort="#Char"/>
                 </term>
                 <term op=".KList" sort="KList"/>
                </term>
                <term op="_`(_`)" sort="KItem">
                 <term op="'SMALLINT" sort="KLabel"/>
                 <term op=".KList" sort="KList"/>
                </term>
               </term>
               <term op="_|->_" sort="MapItem">
                <term op="_`(_`)" sort="KItem">
                 <term op="#token" sort="KLabel">
                  <term op="&quot;Id&quot;" sort="#String"/>
                  <term op="&quot;Anno&quot;" sort="#String"/>
                 </term>
                 <term op=".KList" sort="KList"/>
                </term>
                <term op="_`(_`)" sort="KItem">
                 <term op="'SMALLINT" sort="KLabel"/>
                 <term op=".KList" sort="KList"/>
                </term>
               </term>
               <term op="_|->_" sort="MapItem">
                <term op="_`(_`)" sort="KItem">
                 <term op="#token" sort="KLabel">
                  <term op="&quot;Id&quot;" sort="#String"/>
                  <term op="&quot;B&quot;" sort="#Char"/>
                 </term>
                 <term op=".KList" sort="KList"/>
                </term>
                <term op="_`(_`)" sort="KItem">
                 <term op="'SMALLINT" sort="KLabel"/>
                 <term op=".KList" sort="KList"/>
                </term>
               </term>
               <term op="_|->_" sort="MapItem">
                <term op="_`(_`)" sort="KItem">
                 <term op="#token" sort="KLabel">
                  <term op="&quot;Id&quot;" sort="#String"/>
                  <term op="&quot;Id&quot;" sort="#String"/>
                 </term>
                 <term op=".KList" sort="KList"/>
                </term>
                <term op="_`(_`)" sort="KItem">
                 <term op="'SMALLINT" sort="KLabel"/>
                 <term op=".KList" sort="KList"/>
                </term>
               </term>
              </term>
             </term>
             <term op=".KList" sort="KList"/>
            </term>
            <term op="schema" sort="CellLabel"/>
           </term>
           <term op="&lt;_>_&lt;/_>" sort="BagItem">
            <term op="table-name" sort="CellLabel"/>
            <term op="_`(_`)" sort="KItem">
             <term op="Set2KLabel_" sort="KLabel">
              <term op="SetItem" sort="SetItem">
               <term op="_`(_`)" sort="KItem">
                <term op="#token" sort="KLabel">
                 <term op="&quot;Id&quot;" sort="#String"/>
                 <term op="&quot;Students&quot;" sort="#String"/>
                </term>
                <term op=".KList" sort="KList"/>
               </term>
              </term>
             </term>
             <term op=".KList" sort="KList"/>
            </term>
            <term op="table-name" sort="CellLabel"/>
           </term>
           <term op="&lt;_>_&lt;/_>" sort="BagItem">
            <term op="values" sort="CellLabel"/>
            <term op=".Bag" sort="Bag"/>
            <term op="values" sort="CellLabel"/>
           </term>
          </term>
          <term op="table" sort="CellLabel"/>
         </term>
        </term>
        <term op="tables" sort="CellLabel"/>
       </term>
      </term>
      <term op="database" sort="CellLabel"/>
     </term>
    </term>
    <term op="T" sort="CellLabel"/>
   </term>
   <term op="generatedTop" sort="CellLabel"/>
  </term>
 </result>
 <result total-rewrites="6" real-time-ms="0" cpu-time-ms="0" rewrites-per-second="214285">
  <term op="sNat_" number="1" sort="#NzNat">
   <term op="0" sort="#Zero"/>
  </term>
 </result>
</maudeml>
